jsonschema_marshmallow/__init__.py
jsonschema_marshmallow/dynamic.py
jsonschema_marshmallow/shared.py
jsonschema_marshmallow-0.0.1.dist-info/LICENSE
jsonschema_marshmallow-0.0.1.dist-info/METADATA
jsonschema_marshmallow-0.0.1.dist-info/WHEEL
jsonschema_marshmallow-0.0.1.dist-info/entry_points.txt
jsonschema_marshmallow-0.0.1.dist-info/top_level.txt
jsonschema_marshmallow-0.0.1.dist-info/RECORD
