Metadata-Version: 2.1
Name: jsonschema-marshmallow
Version: 0.0.1
Summary: UNKNOWN
Home-page: UNKNOWN
License: UNKNOWN
Platform: UNKNOWN
License-File: LICENSE
Requires-Dist: marshmallow
